<?xml version="1.0"?>
<FindBugsFilter>
  <!--
    Exclusions in this section have been triaged and determined to be false positives.
  -->
  <Match>
    <Or>
      <!-- We don't care about this behavior -->
      <Bug pattern="CRLF_INJECTION_LOGS"/>
      <!-- Jenkins handles this issue differently or doesn't care about it -->
      <Bug pattern="INFORMATION_EXPOSURE_THROUGH_AN_ERROR_MESSAGE"/>
      <!-- Used for backward compatibility and extending utility classes -->
      <Bug pattern="NM_SAME_SIMPLE_NAME_AS_SUPERCLASS"/>
    </Or>
  </Match>
  <Match>
    <!-- Ignore autogenerated methods -->
    <Bug pattern="NM_METHOD_NAMING_CONVENTION"/>
    <Or>
      <Class name="hudson.tasks.Messages"/>
      <Class name="hudson.tools.Messages"/>
    </Or>
  </Match>
  <!--
    Here lies technical debt. Exclusions in this section have not yet been triaged. When working on
    on this section, pick an exclusion to triage, then:
    - If it is a false positive, add a @SuppressFBWarnings(value = "[…]", justification = "[…]")
      annotation indicating the reason why it is a false positive, then remove the exclusion from
      this section.
    - If it is not a false positive, fix the bug, then remove the exclusion from this section.
  -->
  <Match>
    <And>
      <Bug pattern="DM_DEFAULT_ENCODING"/>
      <Or>
        <Class name="hudson.cli.CLICommand"/>
        <Class name="hudson.cli.CLIConnectionFactory"/>
        <Class name="hudson.cli.GroovyCommand"/>
        <Class name="hudson.cli.GroovyshCommand"/>
        <Class name="hudson.cli.ListChangesCommand"/>
        <Class name="hudson.cli.PrivateKeyProvider"/>
        <Class name="hudson.console.AnnotatedLargeText"/>
        <Class name="hudson.console.ConsoleAnnotationOutputStream"/>
        <Class name="hudson.console.ConsoleNote"/>
        <Class name="hudson.FilePath$CreateTextTempFile"/>
        <Class name="hudson.FilePath$ReadToString"/>
        <Class name="hudson.FilePath$Write"/>
        <Class name="hudson.lifecycle.WindowsServiceLifecycle"/>
        <Class name="hudson.model.FileParameterValue$FileItemImpl"/>
        <Class name="hudson.model.Run"/>
        <Class name="hudson.model.UpdateCenter"/>
        <Class name="hudson.model.UsageStatistics"/>
        <Class name="hudson.Proc$LocalProc"/>
        <Class name="hudson.scm.SCM"/>
        <Class name="hudson.security.csrf.DefaultCrumbIssuer"/>
        <Class name="hudson.security.HudsonAuthenticationEntryPoint"/>
        <Class name="hudson.util.BootFailure"/>
        <Class name="hudson.util.ByteBuffer"/>
        <Class name="hudson.util.CompressedFile"/>
        <Class name="hudson.util.ConsistentHash"/>
        <Class name="hudson.util.IOUtils"/>
        <Class name="hudson.util.LogTaskListener$LogOutputStream"/>
        <Class name="hudson.util.ProcessTree$AIX$AIXProcess"/>
        <Class name="hudson.util.ProcessTree$FreeBSD$FreeBSDProcess"/>
        <Class name="hudson.util.ProcessTree$Linux$LinuxProcess"/>
        <Class name="hudson.util.ProcessTree$Solaris$SolarisProcess"/>
        <Class name="hudson.util.Scrambler"/>
        <Class name="hudson.util.Secret"/>
        <Class name="hudson.util.StreamTaskListener"/>
        <Class name="hudson.util.TextFile"/>
        <Class name="hudson.WebAppMain"/>
        <Class name="jenkins.diagnosis.HsErrPidList"/>
        <Class name="jenkins.security.DefaultConfidentialStore"/>
        <Class name="jenkins.security.s2m.AdminWhitelistRule"/>
        <Class name="jenkins.security.s2m.ConfigDirectory"/>
        <Class name="jenkins.slaves.DefaultJnlpSlaveReceiver"/>
        <Class name="jenkins.slaves.restarter.UnixSlaveRestarter"/>
        <Class name="jenkins.util.JSONSignatureValidator"/>
      </Or>
    </And>
  </Match>
  <Match>
    <Confidence value="2"/>
    <Or>
      <And>
        <Bug pattern="CO_COMPARETO_INCORRECT_FLOATING"/>
        <Class name="jenkins.FilePathFilterAggregator$Entry"/>
      </And>
      <And>
        <Bug pattern="COMMAND_INJECTION"/>
        <Or>
          <Class name="hudson.Launcher$LocalLauncher"/>
          <Class name="hudson.Launcher$RemoteChannelLaunchCallable"/>
          <Class name="hudson.os.WindowsUtil"/>
          <Class name="jenkins.slaves.restarter.WinswSlaveRestarter"/>
        </Or>
      </And>
      <And>
        <Bug pattern="DCN_NULLPOINTER_EXCEPTION"/>
        <Or>
          <Class name="hudson.PluginManager"/>
          <Class name="hudson.TcpSlaveAgentListener"/>
        </Or>
      </And>
      <And>
        <Bug pattern="DM_NUMBER_CTOR"/>
        <Class name="hudson.scheduler.CrontabLexer"/>
      </And>
      <And>
        <Bug pattern="DP_CREATE_CLASSLOADER_INSIDE_DO_PRIVILEGED"/>
        <Or>
          <Class name="hudson.ClassicPluginStrategy"/>
          <Class name="hudson.PluginManager"/>
          <Class name="hudson.WebAppMain"/>
        </Or>
      </And>
      <And>
        <Bug pattern="EC_UNRELATED_TYPES_USING_POINTER_EQUALITY"/>
        <Or>
          <Class name="hudson.model.AutoCompletionCandidates"/>
          <Class name="hudson.tasks.Fingerprinter$FingerprintAction"/>
        </Or>
      </And>
      <Match>
        <Or>
          <Bug pattern="EI_EXPOSE_REP"/>
          <Bug pattern="EI_EXPOSE_REP2"/>
        </Or>
      </Match>
      <And>
        <Bug pattern="EQ_COMPARETO_USE_OBJECT_EQUALS"/>
        <Or>
          <Class name="hudson.ExtensionComponent"/>
          <Class name="hudson.Functions$Tag"/>
          <Class name="hudson.MarkupText$Tag"/>
          <Class name="hudson.model.HealthReport"/>
          <Class name="hudson.model.Queue$WaitingItem"/>
          <Class name="hudson.model.User"/>
          <Class name="hudson.model.View$UserInfo"/>
          <Class name="hudson.PluginWrapper"/>
          <Class name="hudson.util.ConsistentHash$Point"/>
          <Class name="jenkins.FilePathFilterAggregator$Entry"/>
        </Or>
      </And>
      <And>
        <Bug pattern="EQ_DOESNT_OVERRIDE_EQUALS"/>
        <Or>
          <Class name="hudson.model.Run$ArtifactList"/>
          <Class name="hudson.model.Run$SerializableArtifactList"/>
          <Class name="hudson.search.Search$SearchResultImpl"/>
          <Class name="hudson.slaves.NodeList"/>
          <Class name="hudson.util.StreamResource"/>
        </Or>
      </And>
      <And>
        <Bug pattern="EQ_GETCLASS_AND_CLASS_CONSTANT"/>
        <Or>
          <Class name="hudson.model.BooleanParameterDefinition"/>
          <Class name="hudson.model.ChoiceParameterDefinition"/>
          <Class name="hudson.model.FileParameterDefinition"/>
          <Class name="hudson.model.PasswordParameterDefinition"/>
          <Class name="hudson.model.RunParameterDefinition"/>
          <Class name="hudson.model.StringParameterDefinition"/>
          <Class name="hudson.model.TextParameterDefinition"/>
          <Class name="hudson.util.NoClientBindProtocolSocketFactory"/>
        </Or>
      </And>
      <And>
        <Bug pattern="EQ_OVERRIDING_EQUALS_NOT_SYMMETRIC"/>
        <Class name="hudson.cli.BuildCommand$CLICause"/>
      </And>
      <And>
        <Bug pattern="FILE_UPLOAD_FILENAME"/>
        <Or>
          <Class name="hudson.model.FileParameterDefinition"/>
          <Class name="hudson.model.FileParameterValue"/>
          <Class name="hudson.PluginManager"/>
        </Or>
      </And>
      <And>
        <Bug pattern="GROOVY_SHELL"/>
        <Or>
          <Class name="hudson.util.RemotingDiagnostics$Script"/>
          <Class name="jenkins.util.groovy.GroovyHookScript"/>
        </Or>
      </And>
      <And>
        <Bug pattern="HARD_CODE_PASSWORD"/>
        <Class name="hudson.security.AuthenticationProcessingFilter2"/>
      </And>
      <And>
        <Bug pattern="HTTP_PARAMETER_POLLUTION"/>
        <Class name="hudson.ProxyConfiguration$DescriptorImpl"/>
      </And>
      <And>
        <Bug pattern="HTTP_RESPONSE_SPLITTING"/>
        <Or>
          <Class name="hudson.Functions"/>
          <Class name="hudson.security.BasicAuthenticationFilter"/>
          <Class name="jenkins.install.InstallUtil"/>
          <Class name="jenkins.model.Jenkins"/>
          <Class name="jenkins.util.xml.XMLUtils"/>
        </Or>
      </And>
      <And>
        <Bug pattern="IC_INIT_CIRCULARITY"/>
        <Class name="hudson.model.Computer"/>
      </And>
      <And>
        <Bug pattern="INSECURE_COOKIE"/>
        <Or>
          <Class name="hudson.security.SecurityRealm"/>
          <Class name="jenkins.model.Jenkins"/>
        </Or>
      </And>
      <And>
        <Bug pattern="IS2_INCONSISTENT_SYNC"/>
        <Or>
          <Class name="hudson.model.Fingerprint"/>
          <Class name="hudson.model.View"/>
          <Class name="hudson.security.csrf.DefaultCrumbIssuer"/>
          <Class name="hudson.slaves.SimpleScheduledRetentionStrategy"/>
          <Class name="hudson.tasks.Fingerprinter$FingerprintAction"/>
          <Class name="hudson.tools.ToolInstallation"/>
          <Class name="hudson.util.ProcessTree$Darwin$DarwinProcess"/>
          <Class name="hudson.util.SequentialExecutionQueue"/>
          <Class name="hudson.util.SequentialExecutionQueue$QueueEntry"/>
          <Class name="jenkins.model.RunIdMigrator"/>
          <Class name="jenkins.security.apitoken.ApiTokenStats"/>
        </Or>
      </And>
      <And>
        <Bug pattern="IS_FIELD_NOT_GUARDED"/>
        <Or>
          <Class name="hudson.model.ListView"/>
          <Class name="hudson.model.ListView$Listener"/>
        </Or>
      </And>
      <And>
        <Bug pattern="JLM_JSR166_UTILCONCURRENT_MONITORENTER"/>
        <Class name="hudson.PluginManager"/>
      </And>
      <And>
        <Bug pattern="LI_LAZY_INIT_STATIC"/>
        <Or>
          <Class name="hudson.triggers.Trigger"/>
          <Class name="hudson.util.ProcessTree"/>
        </Or>
      </And>
      <And>
        <Bug pattern="LI_LAZY_INIT_UPDATE_STATIC"/>
        <Class name="jenkins.security.UserDetailsCache"/>
      </And>
      <And>
        <Bug pattern="MS_CANNOT_BE_FINAL"/>
        <Or>
          <Class name="hudson.triggers.Trigger"/>
          <Class name="jenkins.model.Jenkins"/>
        </Or>
      </And>
      <And>
        <Bug pattern="MS_EXPOSE_REP"/>
        <Or>
          <Class name="hudson.model.ComputerSet"/>
          <Class name="hudson.model.Fingerprint"/>
          <Class name="hudson.model.PaneStatusProperties"/>
          <Class name="hudson.os.PosixAPI"/>
          <Class name="hudson.security.Permission"/>
          <Class name="hudson.util.FormValidation"/>
          <Class name="hudson.util.ProcessTree"/>
          <Class name="jenkins.tasks.filters.EnvVarsFilterGlobalConfiguration"/>
        </Or>
      </And>
      <And>
        <Bug pattern="MS_MUTABLE_COLLECTION_PKGPROTECT"/>
        <Class name="jenkins.model.Jenkins"/>
      </And>
      <And>
        <Bug pattern="MS_OOI_PKGPROTECT"/>
        <Or>
          <Class name="hudson.util.jna.Advapi32"/>
          <Class name="hudson.util.jna.Options"/>
        </Or>
      </And>
      <And>
        <Bug pattern="MS_PKGPROTECT"/>
        <Or>
          <Class name="hudson.console.ConsoleNote"/>
          <Class name="hudson.model.labels.LabelExpressionParser"/>
          <Class name="hudson.node_monitors.ClockMonitor"/>
          <Class name="hudson.node_monitors.TemporarySpaceMonitor"/>
          <Class name="hudson.scheduler.CrontabParser"/>
          <Class name="hudson.security.ACL"/>
          <Class name="hudson.util.ProcessTree"/>
          <Class name="jenkins.slaves.NioChannelSelector"/>
        </Or>
      </And>
      <And>
        <Bug pattern="MS_SHOULD_BE_FINAL"/>
        <Or>
          <Class name="hudson.Launcher"/>
          <Class name="hudson.Main"/>
          <Class name="hudson.model.UpdateSite"/>
          <Class name="hudson.model.ViewJob"/>
        </Or>
      </And>
      <And>
        <Bug pattern="NP_BOOLEAN_RETURN_NULL"/>
        <Or>
          <Class name="hudson.logging.LogRecorder$Target"/>
          <Class name="hudson.security.SidACL"/>
          <Class name="hudson.security.SparseACL"/>
          <Class name="jenkins.security.stapler.StaplerDispatchValidator"/>
          <Class name="jenkins.YesNoMaybe"/>
        </Or>
      </And>
      <And>
        <Bug pattern="NP_LOAD_OF_KNOWN_NULL_VALUE"/>
        <Or>
          <Class name="jenkins.security.MasterToSlaveCallable"/>
          <Class name="jenkins.util.JSONSignatureValidator"/>
        </Or>
      </And>
      <And>
        <Bug pattern="NP_NONNULL_FIELD_NOT_INITIALIZED_IN_CONSTRUCTOR"/>
        <Class name="jenkins.util.SystemProperties"/>
      </And>
      <And>
        <Bug pattern="NP_NULL_ON_SOME_PATH"/>
        <Or>
          <Class name="hudson.ExtensionList"/>
          <Class name="hudson.model.StringParameterDefinition"/>
          <Class name="hudson.triggers.SCMTrigger"/>
          <Class name="hudson.triggers.SCMTrigger$Runner"/>
        </Or>
      </And>
      <And>
        <Bug pattern="NP_NULL_ON_SOME_PATH_FROM_RETURN_VALUE"/>
        <Or>
          <Class name="hudson.cli.BuildCommand"/>
          <Class name="hudson.cli.DeleteNodeCommand"/>
          <Class name="hudson.cli.UpdateNodeCommand"/>
          <Class name="hudson.cli.WaitNodeOfflineCommand"/>
          <Class name="hudson.cli.WaitNodeOnlineCommand"/>
          <Class name="hudson.FilePath$IsDescendant"/>
          <Class name="hudson.FilePath$MoveAllChildrenTo"/>
          <Class name="hudson.Launcher$RemoteLauncher"/>
          <Class name="hudson.model.AbstractBuild$AbstractBuildExecution"/>
          <Class name="hudson.model.AbstractProject"/>
          <Class name="hudson.model.Build$BuildExecution"/>
          <Class name="hudson.model.Cause$UserIdCause"/>
          <Class name="hudson.model.Computer"/>
          <Class name="hudson.model.Descriptor$HelpRedirect"/>
          <Class name="hudson.model.Descriptor$NewInstanceBindInterceptor"/>
          <Class name="hudson.model.ItemGroupMixIn"/>
          <Class name="hudson.model.Job"/>
          <Class name="hudson.model.Queue"/>
          <Class name="hudson.model.Queue$JobOffer"/>
          <Class name="hudson.model.queue.CauseOfBlockage$BecauseNodeIsBusy"/>
          <Class name="hudson.model.queue.CauseOfBlockage$BecauseNodeIsOffline"/>
          <Class name="hudson.model.queue.MappingWorksheet$ExecutorChunk"/>
          <Class name="hudson.model.queue.WorkUnitContext"/>
          <Class name="hudson.model.ResultTrend"/>
          <Class name="hudson.model.Run"/>
          <Class name="hudson.model.RunParameterValue"/>
          <Class name="hudson.model.Slave"/>
          <Class name="hudson.model.TopLevelItemDescriptor"/>
          <Class name="hudson.model.UpdateCenter$HudsonDowngradeJob"/>
          <Class name="hudson.model.UpdateCenter$HudsonUpgradeJob"/>
          <Class name="hudson.model.UpdateSite$Plugin"/>
          <Class name="hudson.model.UpdateSite$Warning"/>
          <Class name="hudson.model.User"/>
          <Class name="hudson.model.WorkspaceCleanupThread"/>
          <Class name="hudson.PluginManager"/>
          <Class name="hudson.PluginWrapper"/>
          <Class name="hudson.scm.SCM"/>
          <Class name="hudson.security.AuthorizationStrategy"/>
          <Class name="hudson.tasks.BuildTrigger"/>
          <Class name="hudson.tasks.Maven"/>
          <Class name="hudson.tasks.Maven$MavenInstallation"/>
          <Class name="hudson.TcpSlaveAgentListener$TcpSlaveAgentListenerRescheduler"/>
          <Class name="hudson.tools.DownloadFromUrlInstaller$DescriptorImpl"/>
          <Class name="hudson.tools.ToolInstallation"/>
          <Class name="hudson.triggers.SCMTrigger$DescriptorImpl"/>
          <Class name="hudson.util.AtomicFileWriter"/>
          <Class name="hudson.util.DirScanner$Full"/>
          <Class name="hudson.util.KeyedDataStorage"/>
          <Class name="hudson.util.PluginServletFilter"/>
          <Class name="jenkins.fingerprints.FileFingerprintStorage"/>
          <Class name="jenkins.fingerprints.FingerprintStorage"/>
          <Class name="jenkins.install.SetupWizard"/>
          <Class name="jenkins.model.Jenkins"/>
          <Class name="jenkins.model.Nodes"/>
          <Class name="jenkins.model.RunIdMigrator"/>
          <Class name="jenkins.mvn.SettingsPathHelper"/>
          <Class name="jenkins.security.CustomClassFilter$Contributed"/>
          <Class name="jenkins.security.ResourceDomainConfiguration"/>
          <Class name="jenkins.slaves.DefaultJnlpSlaveReceiver"/>
          <Class name="jenkins.util.VirtualFile$FilePathVF"/>
          <Class name="jenkins.util.VirtualFile$FileVF"/>
        </Or>
      </And>
      <And>
        <Bug pattern="NP_NULL_PARAM_DEREF"/>
        <Or>
          <Class name="hudson.model.Run"/>
          <Class name="hudson.PluginManager"/>
        </Or>
      </And>
      <And>
        <Bug pattern="NP_UNWRITTEN_PUBLIC_OR_PROTECTED_FIELD"/>
        <Class name="jenkins.security.apitoken.LegacyApiTokenAdministrativeMonitor"/>
      </And>
      <And>
        <Bug pattern="OBL_UNSATISFIED_OBLIGATION"/>
        <Or>
          <Class name="jenkins.security.s2m.AdminWhitelistRule"/>
          <Class name="jenkins.slaves.StandardOutputSwapper$ChannelSwapper"/>
        </Or>
      </And>
      <And>
        <Bug pattern="OS_OPEN_STREAM"/>
        <Or>
          <Class name="hudson.console.ConsoleNote"/>
          <Class name="jenkins.slaves.DefaultJnlpSlaveReceiver"/>
        </Or>
      </And>
      <And>
        <Bug pattern="PATH_TRAVERSAL_IN"/>
        <Or>
          <Class name="hudson.ClassicPluginStrategy"/>
          <Class name="hudson.cli.InstallPluginCommand"/>
          <Class name="hudson.EnvVars"/>
          <Class name="hudson.FilePath"/>
          <Class name="hudson.FilePath$CopyRecursiveLocal"/>
          <Class name="hudson.FilePath$CopyToWithPermission"/>
          <Class name="hudson.FilePath$CreateTempDir"/>
          <Class name="hudson.FilePath$CreateTempFile"/>
          <Class name="hudson.FilePath$CreateTextTempFile"/>
          <Class name="hudson.FilePath$ExplicitlySpecifiedDirScanner"/>
          <Class name="hudson.FilePath$FileCallableWrapper"/>
          <Class name="hudson.FilePath$IsDescendant"/>
          <Class name="hudson.FilePath$ListGlob"/>
          <Class name="hudson.FilePath$MoveAllChildrenTo"/>
          <Class name="hudson.FilePath$RenameTo"/>
          <Class name="hudson.FilePath$SymlinkTo"/>
          <Class name="hudson.FilePath$UnzipLocal"/>
          <Class name="hudson.init.InitStrategy"/>
          <Class name="hudson.Launcher$LocalLauncher"/>
          <Class name="hudson.Launcher$ProcStarter"/>
          <Class name="hudson.Launcher$RemoteChannelLaunchCallable"/>
          <Class name="hudson.Launcher$RemoteLaunchCallable"/>
          <Class name="hudson.lifecycle.Lifecycle"/>
          <Class name="hudson.lifecycle.WindowsInstallerLink"/>
          <Class name="hudson.lifecycle.WindowsServiceLifecycle"/>
          <Class name="hudson.LocalPluginManager"/>
          <Class name="hudson.logging.LogRecorder"/>
          <Class name="hudson.model.AsyncAperiodicWork"/>
          <Class name="hudson.model.AsyncPeriodicWork"/>
          <Class name="hudson.model.Computer"/>
          <Class name="hudson.model.DirectoryBrowserSupport$IsAbsolute"/>
          <Class name="hudson.model.DownloadService$Downloadable"/>
          <Class name="hudson.model.FileParameterValue"/>
          <Class name="hudson.model.JDK"/>
          <Class name="hudson.model.Job$SubItemBuildsLocationImpl"/>
          <Class name="hudson.model.labels.LabelAtom"/>
          <Class name="hudson.model.Queue"/>
          <Class name="hudson.model.Run"/>
          <Class name="hudson.model.Run$Artifact"/>
          <Class name="hudson.model.UpdateCenter"/>
          <Class name="hudson.model.UpdateCenter$DownloadJob"/>
          <Class name="hudson.model.UpdateCenter$HudsonDowngradeJob"/>
          <Class name="hudson.model.UpdateCenter$InstallationJob"/>
          <Class name="hudson.model.UpdateCenter$PluginDowngradeJob"/>
          <Class name="hudson.model.UpdateCenter$UpdateCenterConfiguration"/>
          <Class name="hudson.model.UpdateSite"/>
          <Class name="hudson.model.UserIdMapper"/>
          <Class name="hudson.Plugin"/>
          <Class name="hudson.PluginManager"/>
          <Class name="hudson.PluginWrapper"/>
          <Class name="hudson.slaves.SlaveComputer$AbsolutePath"/>
          <Class name="hudson.tasks.Fingerprinter$FindRecords"/>
          <Class name="hudson.tasks.Maven$DecideDefaultMavenCommand"/>
          <Class name="hudson.tasks.Maven$MavenInstallation"/>
          <Class name="hudson.tasks.Maven$MavenInstallation$GetMavenVersion"/>
          <Class name="hudson.tools.ToolInstallation"/>
          <Class name="hudson.triggers.SafeTimerTask"/>
          <Class name="hudson.Util"/>
          <Class name="hudson.util.AtomicFileWriter"/>
          <Class name="hudson.util.CompressedFile"/>
          <Class name="hudson.util.DirScanner$Glob"/>
          <Class name="hudson.util.io.ReopenableRotatingFileOutputStream"/>
          <Class name="hudson.util.io.RewindableRotatingFileOutputStream"/>
          <Class name="hudson.util.IOUtils"/>
          <Class name="hudson.util.jna.Kernel32Utils"/>
          <Class name="hudson.WebAppMain"/>
          <Class name="jenkins.diagnosis.HsErrPidList"/>
          <Class name="jenkins.fingerprints.FileFingerprintStorage"/>
          <Class name="jenkins.install.SetupWizard"/>
          <Class name="jenkins.model.Jenkins"/>
          <Class name="jenkins.model.Nodes"/>
          <Class name="jenkins.model.PeepholePermalink"/>
          <Class name="jenkins.model.RunIdMigrator"/>
          <Class name="jenkins.mvn.FilePathGlobalSettingsProvider"/>
          <Class name="jenkins.mvn.FilePathSettingsProvider"/>
          <Class name="jenkins.mvn.SettingsPathHelper"/>
          <Class name="jenkins.plugins.DetachedPluginsUtil$DetachedPlugin"/>
          <Class name="jenkins.security.ClassFilterImpl"/>
          <Class name="jenkins.security.ConfidentialKey"/>
          <Class name="jenkins.security.DefaultConfidentialStore"/>
          <Class name="jenkins.security.s2m.ConfigDirectory"/>
          <Class name="jenkins.security.stapler.StaplerDispatchValidator$ValidatorCache"/>
          <Class name="jenkins.security.stapler.StaticRoutingDecisionProvider"/>
          <Class name="jenkins.SoloFilePathFilter"/>
          <Class name="jenkins.util.groovy.GroovyHookScript"/>
          <Class name="jenkins.util.io.FileBoolean"/>
          <Class name="jenkins.util.JavaVMArguments"/>
          <Class name="jenkins.util.SystemProperties"/>
          <Class name="jenkins.util.VirtualFile$FilePathVF"/>
          <Class name="jenkins.util.VirtualFile$FileVF"/>
        </Or>
      </And>
      <And>
        <Bug pattern="RCN_REDUNDANT_NULLCHECK_OF_NONNULL_VALUE"/>
        <Or>
          <Class name="hudson.model.Run"/>
          <Class name="hudson.tasks.Fingerprinter"/>
          <Class name="jenkins.model.Jenkins"/>
          <Class name="jenkins.model.lazy.LazyBuildMixIn$RunMixIn"/>
        </Or>
      </And>
      <And>
        <Bug pattern="RCN_REDUNDANT_NULLCHECK_OF_NULL_VALUE"/>
        <Class name="jenkins.util.JSONSignatureValidator"/>
      </And>
      <And>
        <Bug pattern="RCN_REDUNDANT_NULLCHECK_WOULD_HAVE_BEEN_A_NPE"/>
        <Or>
          <Class name="jenkins.model.PeepholePermalink"/>
          <Class name="jenkins.util.io.PathRemover"/>
        </Or>
      </And>
      <And>
        <Bug pattern="REDOS"/>
        <Or>
          <Class name="hudson.model.Computer"/>
          <Class name="jenkins.org.apache.commons.validator.routines.UrlValidator"/>
        </Or>
      </And>
      <And>
        <Bug pattern="REQUESTDISPATCHER_FILE_DISCLOSURE"/>
        <Or>
          <Class name="hudson.cli.CLIAction"/>
          <Class name="hudson.model.AbstractProject"/>
          <Class name="hudson.model.Descriptor"/>
          <Class name="hudson.model.DirectoryBrowserSupport"/>
          <Class name="hudson.model.RSS"/>
          <Class name="hudson.model.Run"/>
          <Class name="hudson.scm.AbstractScmTagAction"/>
          <Class name="hudson.search.Search"/>
          <Class name="hudson.security.BasicAuthenticationFilter"/>
          <Class name="hudson.security.FederatedLoginService$UnclaimedIdentityException"/>
          <Class name="hudson.security.HudsonPrivateSecurityRealm"/>
          <Class name="hudson.slaves.NodeDescriptor"/>
          <Class name="hudson.slaves.SlaveComputer"/>
          <Class name="hudson.util.DoubleLaunchChecker"/>
          <Class name="hudson.util.ErrorObject"/>
          <Class name="hudson.util.HudsonIsLoading"/>
          <Class name="hudson.util.HudsonIsRestarting"/>
          <Class name="hudson.widgets.HistoryWidget"/>
          <Class name="jenkins.management.AdministrativeMonitorsApi"/>
          <Class name="jenkins.model.Jenkins"/>
          <Class name="jenkins.model.ParameterizedJobMixIn"/>
          <Class name="jenkins.slaves.EncryptedSlaveAgentJnlpFile"/>
        </Or>
      </And>
      <And>
        <Bug pattern="RV_RETURN_VALUE_IGNORED"/>
        <Or>
          <Class name="hudson.model.Run"/>
          <Class name="hudson.triggers.SCMTrigger$BuildAction"/>
          <Class name="hudson.triggers.SCMTrigger$SCMAction"/>
        </Or>
      </And>
      <And>
        <Bug pattern="RV_RETURN_VALUE_IGNORED_BAD_PRACTICE"/>
        <Or>
          <Class name="hudson.ClassicPluginStrategy"/>
          <Class name="hudson.FilePath"/>
          <Class name="hudson.FilePath$MoveAllChildrenTo"/>
          <Class name="hudson.init.impl.InitialUserContent"/>
          <Class name="hudson.lifecycle.Lifecycle"/>
          <Class name="hudson.lifecycle.WindowsInstallerLink"/>
          <Class name="hudson.Main"/>
          <Class name="hudson.model.Computer"/>
          <Class name="hudson.model.DownloadService$Downloadable"/>
          <Class name="hudson.model.FileParameterValue$FileItemImpl"/>
          <Class name="hudson.model.ItemGroupMixIn"/>
          <Class name="hudson.model.Job"/>
          <Class name="hudson.model.Queue"/>
          <Class name="hudson.model.RunMap"/>
          <Class name="hudson.model.UpdateCenter$DownloadJob"/>
          <Class name="hudson.model.UpdateCenter$InstallationJob"/>
          <Class name="hudson.model.UpdateCenter$PluginDowngradeJob"/>
          <Class name="hudson.PluginManager"/>
          <Class name="hudson.PluginWrapper"/>
          <Class name="hudson.util.CompressedFile"/>
          <Class name="hudson.util.io.ReopenableRotatingFileOutputStream"/>
          <Class name="hudson.util.io.RewindableRotatingFileOutputStream"/>
          <Class name="hudson.util.RemotingDiagnostics$GetHeapDump"/>
          <Class name="hudson.util.TextFile"/>
          <Class name="hudson.WebAppMain"/>
          <Class name="hudson.XmlFile"/>
          <Class name="jenkins.agents.WebSocketAgents$Session"/>
          <Class name="jenkins.diagnosis.HsErrPidFile"/>
          <Class name="jenkins.fingerprints.FileFingerprintStorage"/>
          <Class name="jenkins.install.InstallUtil"/>
          <Class name="jenkins.management.AsynchronousAdministrativeMonitor"/>
          <Class name="jenkins.model.Jenkins"/>
          <Class name="jenkins.slaves.restarter.JnlpSlaveRestarterInstaller"/>
          <Class name="jenkins.util.AtmostOneTaskExecutor"/>
          <Class name="jenkins.util.io.FileBoolean"/>
        </Or>
      </And>
      <And>
        <Bug pattern="RV_RETURN_VALUE_IGNORED_NO_SIDE_EFFECT"/>
        <Or>
          <Class name="hudson.model.queue.BackFiller"/>
          <Class name="hudson.model.queue.CauseOfBlockage"/>
          <Class name="hudson.security.AuthenticationProcessingFilter2"/>
        </Or>
      </And>
      <And>
        <Bug pattern="SBSC_USE_STRINGBUFFER_CONCATENATION"/>
        <Or>
          <Class name="hudson.model.AutoCompletionCandidates"/>
          <Class name="hudson.model.DirectoryBrowserSupport"/>
        </Or>
      </And>
      <And>
        <Bug pattern="SE_BAD_FIELD"/>
        <Class name="hudson.scm.PollingResult"/>
      </And>
      <And>
        <Bug pattern="SE_INNER_CLASS"/>
        <Or>
          <Class name="hudson.util.ProcessTree$Remote$RemoteProcess"/>
          <Class name="hudson.util.ProcessTree$SerializedProcess"/>
        </Or>
      </And>
      <And>
        <Bug pattern="SE_NO_SERIALVERSIONID"/>
        <Or>
          <Class name="hudson.util.RemotingDiagnostics$Script"/>
          <Class name="jenkins.security.NonSerializableSecurityContext"/>
        </Or>
      </And>
      <And>
        <Bug pattern="SIC_INNER_SHOULD_BE_STATIC"/>
        <Or>
          <Class name="hudson.diagnosis.MemoryUsageMonitor$MemoryGroup"/>
          <Class name="hudson.FilePath$Unpack"/>
          <Class name="hudson.FilePath$ValidateAntFileMask"/>
          <Class name="hudson.model.Queue$StubItem"/>
          <Class name="hudson.PluginManager$FileUploadPluginCopier"/>
          <Class name="hudson.PluginManager$UrlPluginCopier"/>
          <Class name="hudson.tasks.LogRotator$CollatedLogRotatorException"/>
          <Class name="hudson.triggers.SlowTriggerAdminMonitor$Value"/>
        </Or>
      </And>
      <And>
        <Bug pattern="SR_NOT_CHECKED"/>
        <Class name="hudson.org.apache.tools.tar.TarInputStream"/>
      </And>
      <And>
        <Bug pattern="STATIC_IV"/>
        <Or>
          <Class name="hudson.cli.Connection"/>
          <Class name="hudson.model.UsageStatistics$CombinedCipherOutputStream"/>
          <Class name="jenkins.security.CryptoConfidentialKey"/>
        </Or>
      </And>
      <And>
        <Bug pattern="ST_WRITE_TO_STATIC_FROM_INSTANCE_METHOD"/>
        <Or>
          <Class name="hudson.model.FreeStyleProject$DescriptorImpl"/>
          <Class name="hudson.node_monitors.ClockMonitor$DescriptorImpl"/>
          <Class name="hudson.node_monitors.SwapSpaceMonitor$DescriptorImpl"/>
          <Class name="hudson.node_monitors.TemporarySpaceMonitor$DescriptorImpl"/>
          <Class name="hudson.security.FullControlOnceLoggedInAuthorizationStrategy$DescriptorImpl"/>
          <Class name="hudson.security.LegacySecurityRealm$DescriptorImpl"/>
          <Class name="hudson.slaves.JNLPLauncher$DescriptorImpl"/>
          <Class name="hudson.slaves.SlaveComputer$SlaveInitializer"/>
          <Class name="hudson.tasks.ArtifactArchiver$DescriptorImpl"/>
          <Class name="hudson.tasks.Maven$DescriptorImpl"/>
          <Class name="jenkins.security.QueueItemAuthenticatorMonitor"/>
          <Class name="jenkins.security.UserDetailsCache"/>
          <Class name="jenkins.slaves.NioChannelSelector"/>
        </Or>
      </And>
      <And>
        <Bug pattern="SWL_SLEEP_WITH_LOCK_HELD"/>
        <Class name="hudson.model.AbstractItem"/>
      </And>
      <And>
        <Bug pattern="UG_SYNC_SET_UNSYNC_GET"/>
        <Or>
          <Class name="hudson.model.ListView"/>
          <Class name="jenkins.security.s2m.ConfigFile"/>
        </Or>
      </And>
      <And>
        <Bug pattern="UNENCRYPTED_SERVER_SOCKET"/>
        <Class name="hudson.slaves.Channels"/>
      </And>
      <And>
        <Bug pattern="UNENCRYPTED_SOCKET"/>
        <Or>
          <Class name="hudson.TcpSlaveAgentListener"/>
          <Class name="hudson.util.NoClientBindProtocolSocketFactory"/>
        </Or>
      </And>
      <And>
        <Bug pattern="UNSAFE_HASH_EQUALS"/>
        <Or>
          <Class name="jenkins.install.SetupWizard"/>
          <Class name="jenkins.security.apitoken.ApiTokenStore"/>
          <Class name="jenkins.security.ApiTokenProperty"/>
          <Class name="jenkins.security.ApiTokenProperty$DescriptorImpl"/>
          <Class name="jenkins.util.SystemProperties"/>
        </Or>
      </And>
      <And>
        <Bug pattern="URF_UNREAD_FIELD"/>
        <Or>
          <Class name="hudson.model.Cause$LegacyCodeCause"/>
          <Class name="jenkins.util.DirectedGraph$Node"/>
        </Or>
      </And>
      <And>
        <Bug pattern="URF_UNREAD_PUBLIC_OR_PROTECTED_FIELD"/>
        <Or>
          <Class name="hudson.model.UpdateCenter$CompleteBatchJob"/>
          <Class name="hudson.org.apache.tools.tar.TarOutputStream"/>
          <Class name="hudson.search.Search$Item"/>
          <Class name="hudson.security.HudsonPrivateSecurityRealm$SignupInfo"/>
          <Class name="hudson.triggers.SCMTrigger$BuildAction"/>
          <Class name="hudson.widgets.HistoryWidget"/>
          <Class name="jenkins.model.Jenkins"/>
          <Class name="jenkins.model.ModelObjectWithContextMenu$ContextMenu"/>
          <Class name="jenkins.model.ModelObjectWithContextMenu$MenuItem"/>
          <Class name="jenkins.util.groovy.AbstractGroovyViewModule"/>
          <Class name="jenkins.widgets.HistoryPageFilter"/>
        </Or>
      </And>
      <And>
        <Bug pattern="URLCONNECTION_SSRF_FD"/>
        <Or>
          <Class name="hudson.FilePath"/>
          <Class name="hudson.FilePath$Unpack"/>
          <Class name="hudson.Main"/>
          <Class name="hudson.model.Descriptor"/>
          <Class name="hudson.model.Slave$JnlpJar"/>
          <Class name="hudson.PluginManager"/>
          <Class name="hudson.PluginWrapper"/>
          <Class name="hudson.ProxyConfiguration"/>
          <Class name="jenkins.security.ResourceDomainConfiguration"/>
        </Or>
      </And>
      <And>
        <Bug pattern="UR_UNINIT_READ_CALLED_FROM_SUPER_CONSTRUCTOR"/>
        <Class name="hudson.slaves.SlaveComputer"/>
      </And>
      <And>
        <Bug pattern="UWF_UNWRITTEN_PUBLIC_OR_PROTECTED_FIELD"/>
        <Or>
          <Class name="hudson.security.HudsonPrivateSecurityRealm$SignupInfo"/>
          <Class name="jenkins.security.apitoken.LegacyApiTokenAdministrativeMonitor$RevokeAllSelectedModel"/>
          <Class name="jenkins.security.apitoken.LegacyApiTokenAdministrativeMonitor$RevokeAllSelectedUserAndUuid"/>
        </Or>
      </And>
      <And>
        <Bug pattern="VO_VOLATILE_INCREMENT"/>
        <Class name="hudson.util.RingBufferLogHandler"/>
      </And>
      <And>
        <Bug pattern="WA_AWAIT_NOT_IN_LOOP"/>
        <Class name="hudson.model.Queue"/>
      </And>
      <And>
        <Bug pattern="WA_NOT_IN_LOOP"/>
        <Class name="hudson.model.ResourceController"/>
      </And>
      <And>
        <Bug pattern="WEAK_MESSAGE_DIGEST_SHA1"/>
        <Or>
          <Class name="hudson.model.UpdateCenter$UpdateCenterConfiguration"/>
          <Class name="jenkins.util.JSONSignatureValidator"/>
        </Or>
      </And>
      <And>
        <Bug pattern="XSS_SERVLET"/>
        <Or>
          <Class name="hudson.Functions"/>
          <Class name="hudson.security.AccessDeniedException3"/>
        </Or>
      </And>
      <And>
        <Bug pattern="XXE_DOCUMENT"/>
        <Class name="jenkins.util.xml.XMLUtils"/>
      </And>
      <And>
        <Bug pattern="XXE_DTD_TRANSFORM_FACTORY"/>
        <Class name="hudson.WebAppMain"/>
      </And>
      <And>
        <Bug pattern="XXE_SAXPARSER"/>
        <Or>
          <Class name="hudson.PluginManager"/>
          <Class name="hudson.XmlFile"/>
        </Or>
      </And>
      <And>
        <Bug pattern="XXE_XSLT_TRANSFORM_FACTORY"/>
        <Class name="hudson.WebAppMain"/>
      </And>
    </Or>
  </Match>
</FindBugsFilter>
