<pkgref spec="1.12" uuid="A08D3475-52F7-41CE-BB1B-9066D36C881B"><config><identifier>org.jenkins-ci.jenkins.osx.pkg</identifier><version>1.1405</version><description></description><post-install type="none"/><requireAuthorization/><installFrom mod="true">/path/to/jenkins.war</installFrom><installTo mod="true">/Applications/Jenkins</installTo><flags><followSymbolicLinks/><discardResourceForks/><mod>discardResourceForks</mod></flags><packageStore type="internal"></packageStore><mod>installFrom.isAbsoluteType</mod><mod>scripts.postinstall.isAbsoluteType</mod><mod>installTo</mod><mod>scripts.postinstall.path</mod><mod>scripts.postinstall.isRelativeType</mod><mod>installFrom.isRelativeType</mod><mod>version</mod><mod>parent</mod><mod>scripts.scriptsDirectoryPath.path</mod><mod>requireAuthorization</mod><mod>identifier</mod><mod>installFrom.path</mod><mod>extraFiles</mod><mod>installTo.path</mod><mod>postInstall</mod></config><scripts><postinstall relative="true" mod="true">scripts/postinstall-war</postinstall><scripts-element/></scripts><contents><file-list>01jenkins-contents.xml</file-list><filter>/CVS$</filter><filter>/\.svn$</filter><filter>/\.cvsignore$</filter><filter>/\.cvspass$</filter><filter>/\.DS_Store$</filter></contents><extra-files/></pkgref>